find_frame_tv.py
find_frame_tv-0.1.0.dist-info/METADATA
find_frame_tv-0.1.0.dist-info/WHEEL
find_frame_tv-0.1.0.dist-info/entry_points.txt
find_frame_tv-0.1.0.dist-info/licenses/LICENSE
find_frame_tv-0.1.0.dist-info/RECORD
