Metadata-Version: 2.4
Name: find-frame-tv
Version: 0.1.0
Summary: Finds Samsung Frame TVs on a local network using UPnP (Simple Service Discovery Protocol)
Project-URL: Repository, https://github.com/seshness/find-frame-tv
Author-email: Seshadri Mahalingam <seshadri.mahalingam@gmail.com>
License: BSD 3-Clause License
License-File: LICENSE
Keywords: frame,samsung,ssdp,tv,upnp
Classifier: Development Status :: 3 - Alpha
Classifier: Intended Audience :: Developers
Classifier: Programming Language :: Python :: 3
Requires-Python: >=3.13
Requires-Dist: requests>=2.32.3
